netrun/__init__.py
netrun/websocket/__init__.py
netrun/websocket/auth.py
netrun/websocket/connection_manager.py
netrun/websocket/heartbeat.py
netrun/websocket/metrics.py
netrun/websocket/protocol.py
netrun/websocket/reconnection.py
netrun/websocket/session_manager.py
netrun_websocket-1.0.0.dist-info/METADATA
netrun_websocket-1.0.0.dist-info/WHEEL
netrun_websocket-1.0.0.dist-info/licenses/LICENSE
netrun_websocket-1.0.0.dist-info/RECORD
