Metadata-Version: 2.4
Name: netrun-websocket
Version: 1.0.0
Summary: Production-grade WebSocket connection management for Netrun Systems services
Project-URL: Homepage, https://netrunsystems.com
Project-URL: Documentation, https://github.com/netrunsystems/netrun-websocket
Project-URL: Repository, https://github.com/netrunsystems/netrun-websocket
Project-URL: Issues, https://github.com/netrunsystems/netrun-websocket/issues
Author-email: Daniel Garza <daniel@netrunsystems.com>
Maintainer-email: Netrun Systems <engineering@netrunsystems.com>
License: MIT
License-File: LICENSE
Keywords: authentication,connection-pool,fastapi,heartbeat,jwt,namespace,netrun,reconnection,redis,session-management,starlette,websocket
Classifier: Development Status :: 5 - Production/Stable
Classifier: Framework :: AsyncIO
Classifier: Framework :: FastAPI
Classifier: Intended Audience :: Developers
Classifier: License :: OSI Approved :: MIT License
Classifier: Programming Language :: Python :: 3
Classifier: Programming Language :: Python :: 3.10
Classifier: Programming Language :: Python :: 3.11
Classifier: Programming Language :: Python :: 3.12
Classifier: Topic :: Internet :: WWW/HTTP :: Dynamic Content
Classifier: Topic :: Software Development :: Libraries :: Python Modules
Classifier: Typing :: Typed
Requires-Python: >=3.10
Requires-Dist: fastapi>=0.109.0
Requires-Dist: pydantic<3.0.0,>=2.0.0
Requires-Dist: starlette>=0.27.0
Provides-Extra: all
Requires-Dist: python-jose[cryptography]>=3.3.0; extra == 'all'
Requires-Dist: redis[asyncio]<6.0.0,>=5.0.0; extra == 'all'
Provides-Extra: auth
Requires-Dist: python-jose[cryptography]>=3.3.0; extra == 'auth'
Provides-Extra: dev
Requires-Dist: black>=24.0.0; extra == 'dev'
Requires-Dist: mypy>=1.9.0; extra == 'dev'
Requires-Dist: pytest-asyncio>=0.23.0; extra == 'dev'
Requires-Dist: pytest-cov>=4.1.0; extra == 'dev'
Requires-Dist: pytest>=8.0.0; extra == 'dev'
Requires-Dist: python-jose[cryptography]>=3.3.0; extra == 'dev'
Requires-Dist: redis[asyncio]<6.0.0,>=5.0.0; extra == 'dev'
Requires-Dist: ruff>=0.3.0; extra == 'dev'
Provides-Extra: redis
Requires-Dist: redis[asyncio]<6.0.0,>=5.0.0; extra == 'redis'
